LICENSE
MANIFEST.in
README
setup.py
flask_skel.egg-info/PKG-INFO
flask_skel.egg-info/SOURCES.txt
flask_skel.egg-info/dependency_links.txt
flask_skel.egg-info/entry_points.txt
flask_skel.egg-info/not-zip-safe
flask_skel.egg-info/requires.txt
flask_skel.egg-info/top_level.txt
flaskskel/__init__.py
flaskskel/template.py
flaskskel/templates/default_project/manage.py_tmpl
flaskskel/templates/default_project/requirements.txt
flaskskel/templates/default_project/+flask_project_name+/__init__.py_tmpl
flaskskel/templates/default_project/+flask_project_name+/config.py_tmpl
flaskskel/templates/default_project/+flask_project_name+/local_config.py
flaskskel/templates/default_project/+flask_project_name+/blueprints/__init__.py
flaskskel/templates/default_project/+flask_project_name+/blueprints/home.py
flaskskel/templates/default_project/+flask_project_name+/static/favicon.ico
flaskskel/templates/default_project/+flask_project_name+/static/robots.txt
flaskskel/templates/default_project/+flask_project_name+/static/css/README
flaskskel/templates/default_project/+flask_project_name+/static/js/README
flaskskel/templates/default_project/+flask_project_name+/templates/README