Metadata-Version: 1.0
Name: flask-skel
Version: 0.3
Summary: Basic Flask paster skeleton template
Home-page: http://bitbucket.org/eka/flask-skel/
Author: Esteban Feldman
Author-email: esteban.feldman@gmail.com
License: BSD
Keywords: wsgi,flask,web development,mongoengine,paster
Platform: UNKNOWN
Classifier: Intended Audience :: Developers
Classifier: License :: OSI Approved :: BSD License
Classifier: Topic :: Internet :: WWW/HTTP
Classifier: Topic :: Internet :: WWW/HTTP :: WSGI
